{"ongoing_trials": {"tuner0": "0026"}, "hyperparameters": {"space": [{"class_name": "Int", "config": {"name": "num_layers", "default": null, "conditions": [], "min_value": 1, "max_value": 6, "step": 1, "sampling": "linear"}}, {"class_name": "Choice", "config": {"name": "neurons_1", "default": 32, "conditions": [], "values": [32, 64, 128, 264], "ordered": true}}, {"class_name": "Choice", "config": {"name": "activation_1", "default": "relu", "conditions": [], "values": ["relu", "tanh", "sigmoid", "softmax"], "ordered": false}}, {"class_name": "Choice", "config": {"name": "learning_rate", "default": 0.01, "conditions": [], "values": [0.01, 0.001, 0.0001], "ordered": true}}, {"class_name": "Choice", "config": {"name": "neurons_2", "default": 32, "conditions": [], "values": [32, 64, 128, 264], "ordered": true}}, {"class_name": "Choice", "config": {"name": "activation_2", "default": "relu", "conditions": [], "values": ["relu", "tanh", "sigmoid", "softmax"], "ordered": false}}, {"class_name": "Choice", "config": {"name": "neurons_3", "default": 32, "conditions": [], "values": [32, 64, 128, 264], "ordered": true}}, {"class_name": "Choice", "config": {"name": "activation_3", "default": "relu", "conditions": [], "values": ["relu", "tanh", "sigmoid", "softmax"], "ordered": false}}, {"class_name": "Choice", "config": {"name": "neurons_4", "default": 32, "conditions": [], "values": [32, 64, 128, 264], "ordered": true}}, {"class_name": "Choice", "config": {"name": "activation_4", "default": "relu", "conditions": [], "values": ["relu", "tanh", "sigmoid", "softmax"], "ordered": false}}, {"class_name": "Choice", "config": {"name": "neurons_5", "default": 32, "conditions": [], "values": [32, 64, 128, 264], "ordered": true}}, {"class_name": "Choice", "config": {"name": "activation_5", "default": "relu", "conditions": [], "values": ["relu", "tanh", "sigmoid", "softmax"], "ordered": false}}, {"class_name": "Choice", "config": {"name": "neurons_6", "default": 32, "conditions": [], "values": [32, 64, 128, 264], "ordered": true}}, {"class_name": "Choice", "config": {"name": "activation_6", "default": "relu", "conditions": [], "values": ["relu", "tanh", "sigmoid", "softmax"], "ordered": false}}], "values": {"num_layers": 1, "neurons_1": 32, "activation_1": "relu", "learning_rate": 0.01, "neurons_2": 32, "activation_2": "relu", "neurons_3": 32, "activation_3": "relu", "neurons_4": 32, "activation_4": "relu", "neurons_5": 32, "activation_5": "relu", "neurons_6": 32, "activation_6": "relu"}}, "start_order": ["0000", "0001", "0002", "0003", "0004", "0005", "0006", "0007", "0008", "0009", "0010", "0011", "0012", "0013", "0014", "0015", "0016", "0017", "0018", "0019", "0020", "0021", "0022", "0023", "0024", "0025", "0026"], "end_order": ["0000", "0001", "0002", "0003", "0004", "0005", "0006", "0007", "0008", "0009", "0010", "0011", "0012", "0013", "0014", "0015", "0016", "0017", "0018", "0019", "0020", "0021", "0022", "0023", "0024", "0025"], "run_times": {"0000": 1, "0001": 1, "0002": 1, "0003": 1, "0004": 1, "0005": 1, "0006": 1, "0007": 1, "0008": 1, "0009": 1, "0010": 1, "0011": 1, "0012": 1, "0013": 1, "0014": 1, "0015": 1, "0016": 1, "0017": 1, "0018": 1, "0019": 1, "0020": 1, "0021": 1, "0022": 1, "0023": 1, "0024": 1, "0025": 1}, "retry_queue": [], "seed": 3801, "seed_state": 4063, "tried_so_far": ["2481684a41281e026ae3eeb61b6dd8e8", "5bab3ba9a0137b715d438e43953d1838", "caad26c91d33c9c7e2dc0471b69fef40", "f5cdb4c3a26727c9f3bbb4ade7a12dba", "2d3d3877c918b37224bcc0bed19d7bff", "8f2a571cd6a185ce1269eaa14973765c", "c7bb730484c79e6924fa8d140b442d8e", "fb3fb4709eafc3e1f97b4c64bd9f2a29", "c34a127745fe47f15c5081db7aa10b1c", "bc8dc42cb4560aa5dbae17b74f1d5f68", "54f73fe330a67c27a5bf178f598a30ae", "be74169f865a5d059c024ffa8327c553", "a74ed7314a84efa6771afa0b4e2ecd60", "96e4ecb81903a307da110bb3f3bb1e9a", "65ae1220a7b631fa0a203558960b5759", "59a036bf12576394dc13c9cb8733162b", "124a3444f17d0d428dab519b4fb55900", "3066545cbee76199c4b612f9d7ce4d4d", "76a91da881b942f14f8d638fcf8273a9", "afed956746b494214886df437341ffcf", "525a5bea89191273b38a1664a204c258", "f8c163025627222b7736bb887a18e04b", "3d30e98d23e97b181d151ea6c4a062ed", "04e93da9e16ec4654135d5e20addc4dc", "7a2b7d06247f22e88631caa30a1ee5eb", "54a470213a26a5ac9964c3b0d556c30e", "324034c628b643e8e4dcbd1ee9e17697"], "id_to_hash": {"0000": "2481684a41281e026ae3eeb61b6dd8e8", "0001": "c7bb730484c79e6924fa8d140b442d8e", "0002": "c34a127745fe47f15c5081db7aa10b1c", "0003": "76a91da881b942f14f8d638fcf8273a9", "0004": "525a5bea89191273b38a1664a204c258", "0005": "3066545cbee76199c4b612f9d7ce4d4d", "0006": "2d3d3877c918b37224bcc0bed19d7bff", "0007": "124a3444f17d0d428dab519b4fb55900", "0008": "54f73fe330a67c27a5bf178f598a30ae", "0009": "04e93da9e16ec4654135d5e20addc4dc", "0010": "f8c163025627222b7736bb887a18e04b", "0011": "afed956746b494214886df437341ffcf", "0012": "59a036bf12576394dc13c9cb8733162b", "0013": "f5cdb4c3a26727c9f3bbb4ade7a12dba", "0014": "65ae1220a7b631fa0a203558960b5759", "0015": "be74169f865a5d059c024ffa8327c553", "0016": "caad26c91d33c9c7e2dc0471b69fef40", "0017": "8f2a571cd6a185ce1269eaa14973765c", "0018": "5bab3ba9a0137b715d438e43953d1838", "0019": "7a2b7d06247f22e88631caa30a1ee5eb", "0020": "bc8dc42cb4560aa5dbae17b74f1d5f68", "0021": "54a470213a26a5ac9964c3b0d556c30e", "0022": "96e4ecb81903a307da110bb3f3bb1e9a", "0023": "3d30e98d23e97b181d151ea6c4a062ed", "0024": "a74ed7314a84efa6771afa0b4e2ecd60", "0025": "324034c628b643e8e4dcbd1ee9e17697", "0026": "fb3fb4709eafc3e1f97b4c64bd9f2a29"}, "display": {"search_start": "2025-01-07T11:52:08.813635", "trial_start": {"0000": "2025-01-07T11:52:08.813635", "0001": "2025-01-07T11:52:17.497299", "0002": "2025-01-07T11:52:28.602519", "0003": "2025-01-07T11:52:49.126769", "0004": "2025-01-07T11:53:04.027121", "0005": "2025-01-07T11:53:11.487678", "0006": "2025-01-07T11:53:26.854975", "0007": "2025-01-07T11:53:53.804333", "0008": "2025-01-07T11:54:06.451485", "0009": "2025-01-07T11:54:18.270279", "0010": "2025-01-07T11:54:55.691708", "0011": "2025-01-07T11:55:03.630975", "0012": "2025-01-07T11:55:14.537517", "0013": "2025-01-07T11:55:30.995901", "0014": "2025-01-07T11:56:15.013965", "0015": "2025-01-07T11:56:24.619390", "0016": "2025-01-07T11:57:09.852347", "0017": "2025-01-07T11:57:46.294209", "0018": "2025-01-07T11:58:37.119741", "0019": "2025-01-07T11:59:00.005987", "0020": "2025-01-07T11:59:30.823780", "0021": "2025-01-07T12:00:48.614615", "0022": "2025-01-07T12:01:09.010360", "0023": "2025-01-07T12:01:41.269711", "0024": "2025-01-07T12:04:14.706307", "0025": "2025-01-07T12:07:22.969491"}, "trial_number": {"0000": 1, "0001": 2, "0002": 3, "0003": 4, "0004": 5, "0005": 6, "0006": 7, "0007": 8, "0008": 9, "0009": 10, "0010": 11, "0011": 12, "0012": 13, "0013": 14, "0014": 15, "0015": 16, "0016": 17, "0017": 18, "0018": 19, "0019": 20, "0020": 21, "0021": 22, "0022": 23, "0023": 24, "0024": 25, "0025": 26}}, "hyperband_iterations": 1, "max_epochs": 20, "min_epochs": 1, "factor": 3, "brackets": [{"bracket_num": 2, "rounds": [[{"past_id": null, "id": "0000"}, {"past_id": null, "id": "0001"}, {"past_id": null, "id": "0002"}, {"past_id": null, "id": "0003"}, {"past_id": null, "id": "0004"}, {"past_id": null, "id": "0005"}, {"past_id": null, "id": "0006"}, {"past_id": null, "id": "0007"}, {"past_id": null, "id": "0008"}, {"past_id": null, "id": "0009"}, {"past_id": null, "id": "0010"}, {"past_id": null, "id": "0011"}], [{"past_id": "0005", "id": "0012"}, {"past_id": "0009", "id": "0013"}, {"past_id": "0004", "id": "0014"}], [{"past_id": "0012", "id": "0015"}]]}, {"bracket_num": 0, "rounds": [[{"past_id": null, "id": "0024"}, {"past_id": null, "id": "0025"}, {"past_id": null, "id": "0026"}]]}], "current_bracket": 0, "current_iteration": 0}